apilogs/__init__.py
apilogs/_version.py
apilogs/bin.py
apilogs/core.py
apilogs/exceptions.py
apilogs/keys.py
apilogs-1.1.dist-info/DESCRIPTION.rst
apilogs-1.1.dist-info/METADATA
apilogs-1.1.dist-info/RECORD
apilogs-1.1.dist-info/WHEEL
apilogs-1.1.dist-info/entry_points.txt
apilogs-1.1.dist-info/metadata.json
apilogs-1.1.dist-info/top_level.txt
