Metadata-Version: 2.0
Name: apilogs
Version: 1.1
Summary: Easy logging and debugging for Amazon API Gateway and AWS Lambda Serverless APIs
Home-page: http://github.com/rpgreen/apilogs
Author: Ryan Green
Author-email: ryang@ryang.ca
License: BSD
Keywords: aws logs cloudwatch api gateway lambda serverless logging
Platform: any
Classifier: Programming Language :: Python :: 3
Classifier: Programming Language :: Python :: 2
Classifier: Development Status :: 4 - Beta
Classifier: Environment :: Web Environment
Classifier: Intended Audience :: Developers
Classifier: License :: OSI Approved :: BSD License
Classifier: Operating System :: OS Independent
Classifier: Topic :: Utilities
Requires-Dist: boto3 (>=1.2.1)
Requires-Dist: python-dateutil (>=2.4.0)
Requires-Dist: termcolor (>=1.1.0)
